[
    {
        "code": "40000",
        "deck_limit": 1,
        "faction_code": "neutral",
        "health": 20,
        "illustrator": "Francesca Baerald",
        "pack_code": "pksc",
        "position": 1,
        "power": 1,
        "quantity": 1,
        "stripped_text": "Spellcaster\nTap to play a site or to draw from your atlas.\nYou start the game with 4 spells in your hand instead of 3.",
        "stripped_title": "Sorcerer",
        "stripped_type_line": "Your Avatar will win, no contest.",
        "text": "Spellcaster\nTap to play a site or to draw from your atlas.\nYou start the game with 4 spells in your hand instead of 3.",
        "title": "Sorcerer",
        "type_code": "avatar",
        "type_line": "Your Avatar will win, no contest.",
        "uniqueness": false
    },
    {
        "code": "40005",
        "deck_limit": 1,
        "faction_code": "neutral",
        "health": 20,
        "illustrator": "Elvira Shakirowa",
        "pack_code": "pksc",
        "position": 2,
        "power": 1,
        "quantity": 1,
        "stripped_text": "Spellcaster\nTap to play a site or to draw from your atlas.\nYou have [Earth][Fire][Water][Wind] threshold.",
        "stripped_title": "Elementalist",
        "stripped_type_line": "Your Avatar rises to the occassion.",
        "text": "Spellcaster\nTap to play a site or to draw from your atlas.\nYou have [Earth][Fire][Water][Wind] threshold.",
        "title": "Elementalist",
        "type_code": "avatar",
        "type_line": "Your Avatar rises to the occassion.",
        "uniqueness": false
    },
    {
        "code": "40006",
        "deck_limit": 1,
        "faction_code": "neutral",
        "health": 20,
        "illustrator": "Drew Tucker",
        "pack_code": "pksc",
        "position": 3,
        "power": 1,
        "quantity": 1,
        "stripped_text": "Spellcaster, Movement +1\nTap to draw once from your atlas.\nThis Avatar may move onto an empty location, placing the top site from your atlas there.",
        "stripped_title": "Pathfinder",
        "stripped_type_line": "Your Avatar finds the way to victory.",
        "text": "Spellcaster, Movement +1\nTap to draw once from your atlas.\nThis Avatar may move onto an empty location, placing the top site from your atlas there.",
        "title": "Pathfinder",
        "type_code": "avatar",
        "type_line": "Your Avatar finds the way to victory.",
        "uniqueness": false
    },
    {
        "code": "40007",
        "deck_limit": 1,
        "faction_code": "neutral",
        "health": 20,
        "illustrator": "Dan Seagrave",
        "pack_code": "pksc",
        "position": 4,
        "power": 1,
        "quantity": 1,
        "stripped_text": "Spellcaster\nTap to play a site or to draw from your atlas.\nWhen you draw a spell, instead draw two and put one back. You may pay 1 life to put a spell back at the bottom of the spellbook instead.",
        "stripped_title": "Seer",
        "stripped_type_line": "Your Avatar prognosticates a certain success.",
        "text": "Spellcaster\nTap to play a site or to draw from your atlas.\nWhen you draw a spell, instead draw two and put one back. You may pay 1 life to put a spell back at the bottom of the spellbook instead.",
        "title": "Seer",
        "type_code": "avatar",
        "type_line": "Your Avatar prognosticates a certain success.",
        "uniqueness": false
    },
    {
        "code": "40008",
        "deck_limit": 1,
        "faction_code": "neutral",
        "health": 20,
        "illustrator": "Dan Seagrave",
        "pack_code": "pksc",
        "position": 5,
        "power": 1,
        "quantity": 1,
        "stripped_text": "Spellcaster\nTap to play a site or to draw from your atlas.\nTap to turn target minion in a cardinal direction into a 0-power frog token. (Once per game.)",
        "stripped_title": "Hex",
        "stripped_type_line": "Your Avatar. An ugly win is still a win.",
        "text": "Spellcaster\nTap to play a site or to draw from your atlas.\nTap to turn target minion in a cardinal direction into a 0-power frog token. (Once per game.)",
        "title": "Hex",
        "type_code": "avatar",
        "type_line": "Your Avatar. An ugly win is still a win.",
        "uniqueness": false
    },
    {
        "code": "40009",
        "deck_limit": 1,
        "faction_code": "neutral",
        "health": 20,
        "illustrator": "Jussi Pylkas",
        "pack_code": "pksc",
        "position": 6,
        "power": 5,
        "quantity": 1,
        "stripped_text": "Tap to play a site or to draw from your atlas.\nWhenever this Battle Mage attacks, you may play a site or draw from your atlas.",
        "stripped_title": "Battle Mage",
        "stripped_type_line": "Your Avatar to win the battle and the war.",
        "text": "Tap to play a site or to draw from your atlas.\nWhenever this Battle Mage attacks, you may play a site or draw from your atlas.",
        "title": "Battle Mage",
        "type_code": "avatar",
        "type_line": "Your Avatar to win the battle and the war.",
        "uniqueness": false
    },
    {
        "code": "40010",
        "deck_limit": 1,
        "faction_code": "neutral",
        "health": 20,
        "illustrator": "Jussi Pylkas",
        "pack_code": "pksc",
        "position": 7,
        "power": 5,
        "quantity": 1,
        "stripped_text": "Tap > Play or draw a site.\nConjure an aura > You may have a nearby aura You control instead become a minion with power equal to its mana cost until end of turn.",
        "stripped_title": "Enchantress",
        "stripped_type_line": "Your Avatar of transcendant triumph.",
        "text": "Tap > Play or draw a site.\nConjure an aura > You may have a nearby aura You control instead become a minion with power equal to its mana cost until end of turn.",
        "title": "Enchantress",
        "type_code": "avatar",
        "type_line": "Your Avatar of transcendant triumph.",
        "uniqueness": false
    }
]
